vendor_connectors/__init__.py
vendor_connectors/cloud_params.py
vendor_connectors/connectors.py
vendor_connectors/anthropic/__init__.py
vendor_connectors/aws/__init__.py
vendor_connectors/aws/codedeploy.py
vendor_connectors/aws/organizations.py
vendor_connectors/aws/s3.py
vendor_connectors/aws/sso.py
vendor_connectors/cursor/__init__.py
vendor_connectors/github/__init__.py
vendor_connectors/google/__init__.py
vendor_connectors/google/billing.py
vendor_connectors/google/cloud.py
vendor_connectors/google/constants.py
vendor_connectors/google/services.py
vendor_connectors/google/workspace.py
vendor_connectors/meshy/README.md
vendor_connectors/meshy/__init__.py
vendor_connectors/meshy/animate.py
vendor_connectors/meshy/animations.py
vendor_connectors/meshy/base.py
vendor_connectors/meshy/jobs.py
vendor_connectors/meshy/logging.py
vendor_connectors/meshy/models.py
vendor_connectors/meshy/retexture.py
vendor_connectors/meshy/rigging.py
vendor_connectors/meshy/text3d.py
vendor_connectors/meshy/agent_tools/__init__.py
vendor_connectors/meshy/agent_tools/base.py
vendor_connectors/meshy/agent_tools/registry.py
vendor_connectors/meshy/agent_tools/tools.py
vendor_connectors/meshy/agent_tools/crewai/__init__.py
vendor_connectors/meshy/agent_tools/crewai/provider.py
vendor_connectors/meshy/agent_tools/mcp/__init__.py
vendor_connectors/meshy/agent_tools/mcp/__main__.py
vendor_connectors/meshy/agent_tools/mcp/provider.py
vendor_connectors/meshy/persistence/__init__.py
vendor_connectors/meshy/persistence/repository.py
vendor_connectors/meshy/persistence/schemas.py
vendor_connectors/meshy/persistence/utils.py
vendor_connectors/meshy/persistence/vector_store.py
vendor_connectors/meshy/webhooks/__init__.py
vendor_connectors/meshy/webhooks/handler.py
vendor_connectors/meshy/webhooks/schemas.py
vendor_connectors/slack/__init__.py
vendor_connectors/vault/__init__.py
vendor_connectors/zoom/__init__.py
vendor_connectors-0.2.0.dist-info/METADATA
vendor_connectors-0.2.0.dist-info/WHEEL
vendor_connectors-0.2.0.dist-info/entry_points.txt
vendor_connectors-0.2.0.dist-info/RECORD
