Metadata-Version: 2.4
Name: vendor-connectors
Version: 0.2.0
Summary: Universal vendor connectors with transparent secret management, including Cursor AI agents, Anthropic Claude, and Meshy AI for 3D assets
Project-URL: Documentation, https://github.com/jbcom/vendor-connectors#readme
Project-URL: Issues, https://github.com/jbcom/vendor-connectors/issues
Project-URL: Source, https://github.com/jbcom/vendor-connectors
Author-email: Jon Bogaty <jon@jonbogaty.com>
Maintainer-email: Jon Bogaty <jon@jonbogaty.com>
License: MIT
Keywords: 3d,aws,connectors,gcp,github,meshy,slack,vault,zoom
Classifier: Development Status :: 4 - Beta
Classifier: Intended Audience :: Developers
Classifier: License :: OSI Approved :: MIT License
Classifier: Programming Language :: Python :: 3
Classifier: Programming Language :: Python :: 3.10
Classifier: Programming Language :: Python :: 3.11
Classifier: Programming Language :: Python :: 3.12
Classifier: Programming Language :: Python :: 3.13
Classifier: Typing :: Typed
Requires-Python: >=3.10
Requires-Dist: boto3>=1.34.0
Requires-Dist: deepmerge>=1.1.0
Requires-Dist: directed-inputs-class>=202511.3.0
Requires-Dist: eval-type-backport>=0.2.0; python_version < '3.10'
Requires-Dist: extended-data-types>=2025.11.164
Requires-Dist: filelock>=3.13.0
Requires-Dist: google-api-python-client>=2.0.0
Requires-Dist: google-cloud-billing>=1.0.0
Requires-Dist: google-cloud-resource-manager>=1.0.0
Requires-Dist: httpx>=0.28.1
Requires-Dist: hvac>=2.0.0
Requires-Dist: lifecyclelogging>=202511.3.0
Requires-Dist: more-itertools>=10.0.0
Requires-Dist: numpy>=1.26.0
Requires-Dist: pydantic>=2.0.0
Requires-Dist: pygithub>=2.0.0
Requires-Dist: python-graphql-client>=0.4.0
Requires-Dist: requests>=2.32.0
Requires-Dist: rich>=14.0.0
Requires-Dist: slack-sdk>=3.0.0
Requires-Dist: tenacity>=9.1.2
Requires-Dist: validators>=0.22.0
Provides-Extra: agents
Requires-Dist: crewai[tools]>=1.5.0; extra == 'agents'
Requires-Dist: mcp>=1.0.0; extra == 'agents'
Provides-Extra: all
Requires-Dist: crewai[tools]>=1.5.0; extra == 'all'
Requires-Dist: fastapi>=0.115.0; extra == 'all'
Requires-Dist: mcp>=1.0.0; extra == 'all'
Requires-Dist: pyngrok>=7.2.2; extra == 'all'
Requires-Dist: sentence-transformers>=3.0.0; extra == 'all'
Requires-Dist: sqlite-vec>=0.1.0; extra == 'all'
Requires-Dist: uvicorn>=0.38.0; extra == 'all'
Provides-Extra: crewai
Requires-Dist: crewai[tools]>=1.5.0; extra == 'crewai'
Provides-Extra: dev
Requires-Dist: mypy>=1.8.0; extra == 'dev'
Requires-Dist: pytest-asyncio>=0.23.0; extra == 'dev'
Requires-Dist: pytest-cov>=5.0.0; extra == 'dev'
Requires-Dist: pytest-mock>=3.14.0; extra == 'dev'
Requires-Dist: pytest>=8.0.0; extra == 'dev'
Requires-Dist: ruff>=0.2.0; extra == 'dev'
Requires-Dist: types-requests>=2.31.0; extra == 'dev'
Provides-Extra: mcp
Requires-Dist: mcp>=1.0.0; extra == 'mcp'
Provides-Extra: tests
Requires-Dist: pytest-asyncio>=0.23.0; extra == 'tests'
Requires-Dist: pytest-cov>=5.0.0; extra == 'tests'
Requires-Dist: pytest-mock>=3.14.0; extra == 'tests'
Requires-Dist: pytest>=8.0.0; extra == 'tests'
Provides-Extra: vector
Requires-Dist: sentence-transformers>=3.0.0; extra == 'vector'
Requires-Dist: sqlite-vec>=0.1.0; extra == 'vector'
Provides-Extra: webhooks
Requires-Dist: fastapi>=0.115.0; extra == 'webhooks'
Requires-Dist: pyngrok>=7.2.2; extra == 'webhooks'
Requires-Dist: uvicorn>=0.38.0; extra == 'webhooks'
